<?xml version="1.0" encoding="ISO-8859-1"?>
<tBestellungen>
  <tBestellung kFirma="1" kBenutzer="1">
    <cSprache>ger</cSprache>
    <cWaehrung>EUR</cWaehrung>
    <cBestellNr/>
    <cExterneBestellNr>PO-076-02524995022710164</cExterneBestellNr>
    <cVersandartName>TEMU</cVersandartName>
    <cVersandInfo/>
    <dVersandDatum/>
    <cTracking/>
    <dLieferDatum/>
    <cKommentar/>
    <cBemerkung/>
    <dErstellt>21.11.2025</dErstellt>
    <cZahlungsartName>TEMU</cZahlungsartName>
    <dBezahltDatum/>
    <twarenkorbpos>
      <cName>ToCi 4 x LED Kerzen Dunkelrot Ø 5 x 7 cm &#8211; Flammenlose Echtwachskerzen mit flackerndem Licht &amp; Timer - LED-Stumpenkerzen mit An-/Ausschalter - Batteriebetriebene Dekokerzen für Advent &amp; Zuhause</cName>
      <cArtNr>2021451277-4</cArtNr>
      <cBarcode/>
      <cEinheit/>
      <fPreisEinzelNetto>16.66000</fPreisEinzelNetto>
      <fPreis>19.83</fPreis>
      <fMwSt>19.00</fMwSt>
      <fAnzahl>1.00</fAnzahl>
      <cPosTyp>standard</cPosTyp>
      <fRabatt>0.00</fRabatt>
    </twarenkorbpos>
    <twarenkorbpos>
      <cName>TEMU Versand</cName>
      <cArtNr/>
      <cBarcode/>
      <cEinheit/>
      <fPreisEinzelNetto>2.51000</fPreisEinzelNetto>
      <fPreis>2.99</fPreis>
      <fMwSt>19.00</fMwSt>
      <fAnzahl>1.00</fAnzahl>
      <cPosTyp>versandkosten</cPosTyp>
      <fRabatt>0.00</fRabatt>
    </twarenkorbpos>
    <tkunde>
      <cKundenNr/>
      <cAnrede/>
      <cTitel/>
      <cVorname>******</cVorname>
      <cNachname>*******</cNachname>
      <cFirma/>
      <cStrasse>*************</cStrasse>
      <cAdressZusatz/>
      <cPLZ>23968	</cPLZ>
      <cOrt>*******</cOrt>
      <cBundesland>**********************</cBundesland>
      <cLand>DE</cLand>
      <cTel/>
      <cMobil/>
      <cFax/>
      <cMail/>
      <cUSTID/>
      <cWWW/>
      <cHerkunft>TEMU</cHerkunft>
      <dErstellt>21.11.2025</dErstellt>
    </tkunde>
    <tlieferadresse>
      <cAnrede/>
      <cVorname>******</cVorname>
      <cNachname>*******</cNachname>
      <cTitel/>
      <cFirma/>
      <cStrasse>*************</cStrasse>
      <cAdressZusatz/>
      <cPLZ>23968	</cPLZ>
      <cOrt>*******</cOrt>
      <cBundesland>**********************</cBundesland>
      <cLand>DE</cLand>
      <cTel/>
      <cMobil/>
      <cFax/>
      <cMail/>
    </tlieferadresse>
    <tzahlungsinfo>
      <cBankName/>
      <cBLZ/>
      <cKontoNr/>
      <cKartenNr/>
      <dGueltigkeit/>
      <cCVV/>
      <cKartenTyp/>
      <cInhaber/>
      <cIBAN/>
      <cBIC/>
    </tzahlungsinfo>
  </tBestellung>
  <tBestellung kFirma="1" kBenutzer="1">
    <cSprache>ger</cSprache>
    <cWaehrung>EUR</cWaehrung>
    <cBestellNr/>
    <cExterneBestellNr>PO-076-02557599935350482</cExterneBestellNr>
    <cVersandartName>TEMU</cVersandartName>
    <cVersandInfo/>
    <dVersandDatum/>
    <cTracking/>
    <dLieferDatum/>
    <cKommentar/>
    <cBemerkung/>
    <dErstellt>20.11.2025</dErstellt>
    <cZahlungsartName>TEMU</cZahlungsartName>
    <dBezahltDatum/>
    <twarenkorbpos>
      <cName>ToCi 4 x LED Kerzen Dunkelrot Ø 5 x 7 cm &#8211; Flammenlose Echtwachskerzen mit flackerndem Licht &amp; Timer - LED-Stumpenkerzen mit An-/Ausschalter - Batteriebetriebene Dekokerzen für Advent &amp; Zuhause</cName>
      <cArtNr>2021451277-4</cArtNr>
      <cBarcode/>
      <cEinheit/>
      <fPreisEinzelNetto>16.66000</fPreisEinzelNetto>
      <fPreis>19.83</fPreis>
      <fMwSt>19.00</fMwSt>
      <fAnzahl>1.00</fAnzahl>
      <cPosTyp>standard</cPosTyp>
      <fRabatt>0.00</fRabatt>
    </twarenkorbpos>
    <twarenkorbpos>
      <cName>TEMU Versand</cName>
      <cArtNr/>
      <cBarcode/>
      <cEinheit/>
      <fPreisEinzelNetto>2.51000</fPreisEinzelNetto>
      <fPreis>2.99</fPreis>
      <fMwSt>19.00</fMwSt>
      <fAnzahl>1.00</fAnzahl>
      <cPosTyp>versandkosten</cPosTyp>
      <fRabatt>0.00</fRabatt>
    </twarenkorbpos>
    <tkunde>
      <cKundenNr/>
      <cAnrede/>
      <cTitel/>
      <cVorname>*******</cVorname>
      <cNachname>******</cNachname>
      <cFirma/>
      <cStrasse>***********</cStrasse>
      <cAdressZusatz/>
      <cPLZ>14712	</cPLZ>
      <cOrt>********</cOrt>
      <cBundesland>***********</cBundesland>
      <cLand>DE</cLand>
      <cTel/>
      <cMobil/>
      <cFax/>
      <cMail/>
      <cUSTID/>
      <cWWW/>
      <cHerkunft>TEMU</cHerkunft>
      <dErstellt>20.11.2025</dErstellt>
    </tkunde>
    <tlieferadresse>
      <cAnrede/>
      <cVorname>*******</cVorname>
      <cNachname>******</cNachname>
      <cTitel/>
      <cFirma/>
      <cStrasse>***********</cStrasse>
      <cAdressZusatz/>
      <cPLZ>14712	</cPLZ>
      <cOrt>********</cOrt>
      <cBundesland>***********</cBundesland>
      <cLand>DE</cLand>
      <cTel/>
      <cMobil/>
      <cFax/>
      <cMail/>
    </tlieferadresse>
    <tzahlungsinfo>
      <cBankName/>
      <cBLZ/>
      <cKontoNr/>
      <cKartenNr/>
      <dGueltigkeit/>
      <cCVV/>
      <cKartenTyp/>
      <cInhaber/>
      <cIBAN/>
      <cBIC/>
    </tzahlungsinfo>
  </tBestellung>
  <tBestellung kFirma="1" kBenutzer="1">
    <cSprache>ger</cSprache>
    <cWaehrung>EUR</cWaehrung>
    <cBestellNr/>
    <cExterneBestellNr>PO-076-02623163123831917</cExterneBestellNr>
    <cVersandartName>TEMU</cVersandartName>
    <cVersandInfo/>
    <dVersandDatum/>
    <cTracking/>
    <dLieferDatum/>
    <cKommentar/>
    <cBemerkung/>
    <dErstellt>20.11.2025</dErstellt>
    <cZahlungsartName>TEMU</cZahlungsartName>
    <dBezahltDatum/>
    <twarenkorbpos>
      <cName>ToCi 4 x LED Kerzen Dunkelrot Ø 5 x 7 cm &#8211; Flammenlose Echtwachskerzen mit flackerndem Licht &amp; Timer - LED-Stumpenkerzen mit An-/Ausschalter - Batteriebetriebene Dekokerzen für Advent &amp; Zuhause</cName>
      <cArtNr>2021451277-4</cArtNr>
      <cBarcode/>
      <cEinheit/>
      <fPreisEinzelNetto>16.66000</fPreisEinzelNetto>
      <fPreis>19.83</fPreis>
      <fMwSt>19.00</fMwSt>
      <fAnzahl>1.00</fAnzahl>
      <cPosTyp>standard</cPosTyp>
      <fRabatt>0.00</fRabatt>
    </twarenkorbpos>
    <twarenkorbpos>
      <cName>TEMU Versand</cName>
      <cArtNr/>
      <cBarcode/>
      <cEinheit/>
      <fPreisEinzelNetto>2.51000</fPreisEinzelNetto>
      <fPreis>2.99</fPreis>
      <fMwSt>19.00</fMwSt>
      <fAnzahl>1.00</fAnzahl>
      <cPosTyp>versandkosten</cPosTyp>
      <fRabatt>0.00</fRabatt>
    </twarenkorbpos>
    <tkunde>
      <cKundenNr/>
      <cAnrede/>
      <cTitel/>
      <cVorname>*******</cVorname>
      <cNachname>******</cNachname>
      <cFirma/>
      <cStrasse>************</cStrasse>
      <cAdressZusatz/>
      <cPLZ>67661	</cPLZ>
      <cOrt>**************</cOrt>
      <cBundesland>***************</cBundesland>
      <cLand>DE</cLand>
      <cTel/>
      <cMobil/>
      <cFax/>
      <cMail/>
      <cUSTID/>
      <cWWW/>
      <cHerkunft>TEMU</cHerkunft>
      <dErstellt>20.11.2025</dErstellt>
    </tkunde>
    <tlieferadresse>
      <cAnrede/>
      <cVorname>*******</cVorname>
      <cNachname>******</cNachname>
      <cTitel/>
      <cFirma/>
      <cStrasse>************</cStrasse>
      <cAdressZusatz/>
      <cPLZ>67661	</cPLZ>
      <cOrt>**************</cOrt>
      <cBundesland>***************</cBundesland>
      <cLand>DE</cLand>
      <cTel/>
      <cMobil/>
      <cFax/>
      <cMail/>
    </tlieferadresse>
    <tzahlungsinfo>
      <cBankName/>
      <cBLZ/>
      <cKontoNr/>
      <cKartenNr/>
      <dGueltigkeit/>
      <cCVV/>
      <cKartenTyp/>
      <cInhaber/>
      <cIBAN/>
      <cBIC/>
    </tzahlungsinfo>
  </tBestellung>
  <tBestellung kFirma="1" kBenutzer="1">
    <cSprache>ger</cSprache>
    <cWaehrung>EUR</cWaehrung>
    <cBestellNr/>
    <cExterneBestellNr>PO-076-03243051200633564</cExterneBestellNr>
    <cVersandartName>TEMU</cVersandartName>
    <cVersandInfo/>
    <dVersandDatum/>
    <cTracking/>
    <dLieferDatum/>
    <cKommentar/>
    <cBemerkung/>
    <dErstellt>24.11.2025</dErstellt>
    <cZahlungsartName>TEMU</cZahlungsartName>
    <dBezahltDatum/>
    <twarenkorbpos>
      <cName>ToCi 4 x LED Kerzen Dunkelrot &#8211; Flammenlose Echtwachskerzen mit flackerndem Licht &amp; Timer - LED-Stumpenkerzen mit An-/Ausschalter - Batteriebetriebene Dekokerzen für Advent &amp; Zuhause</cName>
      <cArtNr>2021451277-4</cArtNr>
      <cBarcode/>
      <cEinheit/>
      <fPreisEinzelNetto>16.66000</fPreisEinzelNetto>
      <fPreis>19.83</fPreis>
      <fMwSt>19.00</fMwSt>
      <fAnzahl>1.00</fAnzahl>
      <cPosTyp>standard</cPosTyp>
      <fRabatt>0.00</fRabatt>
    </twarenkorbpos>
    <twarenkorbpos>
      <cName>TEMU Versand</cName>
      <cArtNr/>
      <cBarcode/>
      <cEinheit/>
      <fPreisEinzelNetto>2.51000</fPreisEinzelNetto>
      <fPreis>2.99</fPreis>
      <fMwSt>19.00</fMwSt>
      <fAnzahl>1.00</fAnzahl>
      <cPosTyp>versandkosten</cPosTyp>
      <fRabatt>0.00</fRabatt>
    </twarenkorbpos>
    <tkunde>
      <cKundenNr/>
      <cAnrede/>
      <cTitel/>
      <cVorname>Jessika</cVorname>
      <cNachname>Kübler</cNachname>
      <cFirma/>
      <cStrasse>Wackerhagen 17</cStrasse>
      <cAdressZusatz/>
      <cPLZ>20537	</cPLZ>
      <cOrt>Hamburg</cOrt>
      <cBundesland>Hamburg</cBundesland>
      <cLand>DE</cLand>
      <cTel/>
      <cMobil/>
      <cFax/>
      <cMail>wo3kzhlbdc13070@eu.shipping.temuemail.com</cMail>
      <cUSTID/>
      <cWWW/>
      <cHerkunft>TEMU</cHerkunft>
      <dErstellt>24.11.2025</dErstellt>
    </tkunde>
    <tlieferadresse>
      <cAnrede/>
      <cVorname>Jessika</cVorname>
      <cNachname>Kübler</cNachname>
      <cTitel/>
      <cFirma/>
      <cStrasse>Wackerhagen 17</cStrasse>
      <cAdressZusatz/>
      <cPLZ>20537	</cPLZ>
      <cOrt>Hamburg</cOrt>
      <cBundesland>Hamburg</cBundesland>
      <cLand>DE</cLand>
      <cTel/>
      <cMobil/>
      <cFax/>
      <cMail>wo3kzhlbdc13070@eu.shipping.temuemail.com</cMail>
    </tlieferadresse>
    <tzahlungsinfo>
      <cBankName/>
      <cBLZ/>
      <cKontoNr/>
      <cKartenNr/>
      <dGueltigkeit/>
      <cCVV/>
      <cKartenTyp/>
      <cInhaber/>
      <cIBAN/>
      <cBIC/>
    </tzahlungsinfo>
  </tBestellung>
  <tBestellung kFirma="1" kBenutzer="1">
    <cSprache>ger</cSprache>
    <cWaehrung>EUR</cWaehrung>
    <cBestellNr/>
    <cExterneBestellNr>PO-076-03299690250872749</cExterneBestellNr>
    <cVersandartName>TEMU</cVersandartName>
    <cVersandInfo/>
    <dVersandDatum/>
    <cTracking/>
    <dLieferDatum/>
    <cKommentar/>
    <cBemerkung/>
    <dErstellt>24.11.2025</dErstellt>
    <cZahlungsartName>TEMU</cZahlungsartName>
    <dBezahltDatum/>
    <twarenkorbpos>
      <cName>ToCi 4 x LED Kerzen Dunkelrot Ø 5 x 7 cm &#8211; Flammenlose Echtwachskerzen mit flackerndem Licht &amp; Timer - LED-Stumpenkerzen mit An-/Ausschalter - Batteriebetriebene Dekokerzen für Advent &amp; Zuhause</cName>
      <cArtNr>2021451277-4</cArtNr>
      <cBarcode/>
      <cEinheit/>
      <fPreisEinzelNetto>16.66000</fPreisEinzelNetto>
      <fPreis>19.83</fPreis>
      <fMwSt>19.00</fMwSt>
      <fAnzahl>1.00</fAnzahl>
      <cPosTyp>standard</cPosTyp>
      <fRabatt>0.00</fRabatt>
    </twarenkorbpos>
    <twarenkorbpos>
      <cName>TEMU Versand</cName>
      <cArtNr/>
      <cBarcode/>
      <cEinheit/>
      <fPreisEinzelNetto>2.51000</fPreisEinzelNetto>
      <fPreis>2.99</fPreis>
      <fMwSt>19.00</fMwSt>
      <fAnzahl>1.00</fAnzahl>
      <cPosTyp>versandkosten</cPosTyp>
      <fRabatt>0.00</fRabatt>
    </twarenkorbpos>
    <tkunde>
      <cKundenNr/>
      <cAnrede/>
      <cTitel/>
      <cVorname>**************</cVorname>
      <cNachname>**************</cNachname>
      <cFirma/>
      <cStrasse>*************</cStrasse>
      <cAdressZusatz/>
      <cPLZ>90431	</cPLZ>
      <cOrt>********</cOrt>
      <cBundesland>******</cBundesland>
      <cLand>DE</cLand>
      <cTel/>
      <cMobil/>
      <cFax/>
      <cMail/>
      <cUSTID/>
      <cWWW/>
      <cHerkunft>TEMU</cHerkunft>
      <dErstellt>24.11.2025</dErstellt>
    </tkunde>
    <tlieferadresse>
      <cAnrede/>
      <cVorname>**************</cVorname>
      <cNachname>**************</cNachname>
      <cTitel/>
      <cFirma/>
      <cStrasse>*************</cStrasse>
      <cAdressZusatz/>
      <cPLZ>90431	</cPLZ>
      <cOrt>********</cOrt>
      <cBundesland>******</cBundesland>
      <cLand>DE</cLand>
      <cTel/>
      <cMobil/>
      <cFax/>
      <cMail/>
    </tlieferadresse>
    <tzahlungsinfo>
      <cBankName/>
      <cBLZ/>
      <cKontoNr/>
      <cKartenNr/>
      <dGueltigkeit/>
      <cCVV/>
      <cKartenTyp/>
      <cInhaber/>
      <cIBAN/>
      <cBIC/>
    </tzahlungsinfo>
  </tBestellung>
  <tBestellung kFirma="1" kBenutzer="1">
    <cSprache>ger</cSprache>
    <cWaehrung>EUR</cWaehrung>
    <cBestellNr/>
    <cExterneBestellNr>PO-076-03340413676152984</cExterneBestellNr>
    <cVersandartName>TEMU</cVersandartName>
    <cVersandInfo/>
    <dVersandDatum/>
    <cTracking/>
    <dLieferDatum/>
    <cKommentar/>
    <cBemerkung/>
    <dErstellt>24.11.2025</dErstellt>
    <cZahlungsartName>TEMU</cZahlungsartName>
    <dBezahltDatum/>
    <twarenkorbpos>
      <cName>ToCi 4 x LED Kerzen Dunkelrot &#8211; Flammenlose Echtwachskerzen mit flackerndem Licht &amp; Timer - LED-Stumpenkerzen mit An-/Ausschalter - Batteriebetriebene Dekokerzen für Advent &amp; Zuhause</cName>
      <cArtNr>2021451277-4</cArtNr>
      <cBarcode/>
      <cEinheit/>
      <fPreisEinzelNetto>16.66000</fPreisEinzelNetto>
      <fPreis>19.83</fPreis>
      <fMwSt>19.00</fMwSt>
      <fAnzahl>1.00</fAnzahl>
      <cPosTyp>standard</cPosTyp>
      <fRabatt>0.00</fRabatt>
    </twarenkorbpos>
    <twarenkorbpos>
      <cName>TEMU Versand</cName>
      <cArtNr/>
      <cBarcode/>
      <cEinheit/>
      <fPreisEinzelNetto>2.51000</fPreisEinzelNetto>
      <fPreis>2.99</fPreis>
      <fMwSt>19.00</fMwSt>
      <fAnzahl>1.00</fAnzahl>
      <cPosTyp>versandkosten</cPosTyp>
      <fRabatt>0.00</fRabatt>
    </twarenkorbpos>
    <tkunde>
      <cKundenNr/>
      <cAnrede/>
      <cTitel/>
      <cVorname>*******</cVorname>
      <cNachname>******</cNachname>
      <cFirma/>
      <cStrasse>***************</cStrasse>
      <cAdressZusatz/>
      <cPLZ>33397	</cPLZ>
      <cOrt>********</cOrt>
      <cBundesland>*******************</cBundesland>
      <cLand>DE</cLand>
      <cTel/>
      <cMobil/>
      <cFax/>
      <cMail/>
      <cUSTID/>
      <cWWW/>
      <cHerkunft>TEMU</cHerkunft>
      <dErstellt>24.11.2025</dErstellt>
    </tkunde>
    <tlieferadresse>
      <cAnrede/>
      <cVorname>*******</cVorname>
      <cNachname>******</cNachname>
      <cTitel/>
      <cFirma/>
      <cStrasse>***************</cStrasse>
      <cAdressZusatz/>
      <cPLZ>33397	</cPLZ>
      <cOrt>********</cOrt>
      <cBundesland>*******************</cBundesland>
      <cLand>DE</cLand>
      <cTel/>
      <cMobil/>
      <cFax/>
      <cMail/>
    </tlieferadresse>
    <tzahlungsinfo>
      <cBankName/>
      <cBLZ/>
      <cKontoNr/>
      <cKartenNr/>
      <dGueltigkeit/>
      <cCVV/>
      <cKartenTyp/>
      <cInhaber/>
      <cIBAN/>
      <cBIC/>
    </tzahlungsinfo>
  </tBestellung>
  <tBestellung kFirma="1" kBenutzer="1">
    <cSprache>ger</cSprache>
    <cWaehrung>EUR</cWaehrung>
    <cBestellNr/>
    <cExterneBestellNr>PO-076-07627727094393062</cExterneBestellNr>
    <cVersandartName>TEMU</cVersandartName>
    <cVersandInfo/>
    <dVersandDatum/>
    <cTracking/>
    <dLieferDatum/>
    <cKommentar/>
    <cBemerkung/>
    <dErstellt>22.11.2025</dErstellt>
    <cZahlungsartName>TEMU</cZahlungsartName>
    <dBezahltDatum/>
    <twarenkorbpos>
      <cName>ToCi 4 x LED Kerzen Dunkelrot Ø 5 x 7 cm &#8211; Flammenlose Echtwachskerzen mit flackerndem Licht &amp; Timer - LED-Stumpenkerzen mit An-/Ausschalter - Batteriebetriebene Dekokerzen für Advent &amp; Zuhause</cName>
      <cArtNr>2021451277-4</cArtNr>
      <cBarcode/>
      <cEinheit/>
      <fPreisEinzelNetto>16.66000</fPreisEinzelNetto>
      <fPreis>19.83</fPreis>
      <fMwSt>19.00</fMwSt>
      <fAnzahl>1.00</fAnzahl>
      <cPosTyp>standard</cPosTyp>
      <fRabatt>0.00</fRabatt>
    </twarenkorbpos>
    <twarenkorbpos>
      <cName>TEMU Versand</cName>
      <cArtNr/>
      <cBarcode/>
      <cEinheit/>
      <fPreisEinzelNetto>2.51000</fPreisEinzelNetto>
      <fPreis>2.99</fPreis>
      <fMwSt>19.00</fMwSt>
      <fAnzahl>1.00</fAnzahl>
      <cPosTyp>versandkosten</cPosTyp>
      <fRabatt>0.00</fRabatt>
    </twarenkorbpos>
    <tkunde>
      <cKundenNr/>
      <cAnrede/>
      <cTitel/>
      <cVorname/>
      <cNachname>****************</cNachname>
      <cFirma/>
      <cStrasse>***********</cStrasse>
      <cAdressZusatz/>
      <cPLZ>96524	</cPLZ>
      <cOrt>*********</cOrt>
      <cBundesland>*********</cBundesland>
      <cLand>DE</cLand>
      <cTel/>
      <cMobil/>
      <cFax/>
      <cMail/>
      <cUSTID/>
      <cWWW/>
      <cHerkunft>TEMU</cHerkunft>
      <dErstellt>22.11.2025</dErstellt>
    </tkunde>
    <tlieferadresse>
      <cAnrede/>
      <cVorname/>
      <cNachname>****************</cNachname>
      <cTitel/>
      <cFirma/>
      <cStrasse>***********</cStrasse>
      <cAdressZusatz/>
      <cPLZ>96524	</cPLZ>
      <cOrt>*********</cOrt>
      <cBundesland>*********</cBundesland>
      <cLand>DE</cLand>
      <cTel/>
      <cMobil/>
      <cFax/>
      <cMail/>
    </tlieferadresse>
    <tzahlungsinfo>
      <cBankName/>
      <cBLZ/>
      <cKontoNr/>
      <cKartenNr/>
      <dGueltigkeit/>
      <cCVV/>
      <cKartenTyp/>
      <cInhaber/>
      <cIBAN/>
      <cBIC/>
    </tzahlungsinfo>
  </tBestellung>
  <tBestellung kFirma="1" kBenutzer="1">
    <cSprache>ger</cSprache>
    <cWaehrung>EUR</cWaehrung>
    <cBestellNr/>
    <cExterneBestellNr>PO-076-07774644721273946</cExterneBestellNr>
    <cVersandartName>TEMU</cVersandartName>
    <cVersandInfo/>
    <dVersandDatum/>
    <cTracking/>
    <dLieferDatum/>
    <cKommentar/>
    <cBemerkung/>
    <dErstellt>22.11.2025</dErstellt>
    <cZahlungsartName>TEMU</cZahlungsartName>
    <dBezahltDatum/>
    <twarenkorbpos>
      <cName>ToCi 4 x LED Kerzen Dunkelrot Ø 5 x 7 cm &#8211; Flammenlose Echtwachskerzen mit flackerndem Licht &amp; Timer - LED-Stumpenkerzen mit An-/Ausschalter - Batteriebetriebene Dekokerzen für Advent &amp; Zuhause</cName>
      <cArtNr>2021451277-4</cArtNr>
      <cBarcode/>
      <cEinheit/>
      <fPreisEinzelNetto>16.66000</fPreisEinzelNetto>
      <fPreis>19.83</fPreis>
      <fMwSt>19.00</fMwSt>
      <fAnzahl>1.00</fAnzahl>
      <cPosTyp>standard</cPosTyp>
      <fRabatt>0.00</fRabatt>
    </twarenkorbpos>
    <twarenkorbpos>
      <cName>TEMU Versand</cName>
      <cArtNr/>
      <cBarcode/>
      <cEinheit/>
      <fPreisEinzelNetto>2.51000</fPreisEinzelNetto>
      <fPreis>2.99</fPreis>
      <fMwSt>19.00</fMwSt>
      <fAnzahl>1.00</fAnzahl>
      <cPosTyp>versandkosten</cPosTyp>
      <fRabatt>0.00</fRabatt>
    </twarenkorbpos>
    <tkunde>
      <cKundenNr/>
      <cAnrede/>
      <cTitel/>
      <cVorname>******</cVorname>
      <cNachname>******</cNachname>
      <cFirma/>
      <cStrasse>************</cStrasse>
      <cAdressZusatz/>
      <cPLZ>14770	</cPLZ>
      <cOrt>************************</cOrt>
      <cBundesland>***********</cBundesland>
      <cLand>DE</cLand>
      <cTel/>
      <cMobil/>
      <cFax/>
      <cMail/>
      <cUSTID/>
      <cWWW/>
      <cHerkunft>TEMU</cHerkunft>
      <dErstellt>22.11.2025</dErstellt>
    </tkunde>
    <tlieferadresse>
      <cAnrede/>
      <cVorname>******</cVorname>
      <cNachname>******</cNachname>
      <cTitel/>
      <cFirma/>
      <cStrasse>************</cStrasse>
      <cAdressZusatz/>
      <cPLZ>14770	</cPLZ>
      <cOrt>************************</cOrt>
      <cBundesland>***********</cBundesland>
      <cLand>DE</cLand>
      <cTel/>
      <cMobil/>
      <cFax/>
      <cMail/>
    </tlieferadresse>
    <tzahlungsinfo>
      <cBankName/>
      <cBLZ/>
      <cKontoNr/>
      <cKartenNr/>
      <dGueltigkeit/>
      <cCVV/>
      <cKartenTyp/>
      <cInhaber/>
      <cIBAN/>
      <cBIC/>
    </tzahlungsinfo>
  </tBestellung>
  <tBestellung kFirma="1" kBenutzer="1">
    <cSprache>ger</cSprache>
    <cWaehrung>EUR</cWaehrung>
    <cBestellNr/>
    <cExterneBestellNr>PO-076-08044892923510289</cExterneBestellNr>
    <cVersandartName>TEMU</cVersandartName>
    <cVersandInfo/>
    <dVersandDatum/>
    <cTracking/>
    <dLieferDatum/>
    <cKommentar/>
    <cBemerkung/>
    <dErstellt>22.11.2025</dErstellt>
    <cZahlungsartName>TEMU</cZahlungsartName>
    <dBezahltDatum/>
    <twarenkorbpos>
      <cName>ToCi 4 x LED Kerzen Dunkelrot Ø 5 x 7 cm &#8211; Flammenlose Echtwachskerzen mit flackerndem Licht &amp; Timer - LED-Stumpenkerzen mit An-/Ausschalter - Batteriebetriebene Dekokerzen für Advent &amp; Zuhause</cName>
      <cArtNr>2021451277-4</cArtNr>
      <cBarcode/>
      <cEinheit/>
      <fPreisEinzelNetto>16.66000</fPreisEinzelNetto>
      <fPreis>19.83</fPreis>
      <fMwSt>19.00</fMwSt>
      <fAnzahl>1.00</fAnzahl>
      <cPosTyp>standard</cPosTyp>
      <fRabatt>0.00</fRabatt>
    </twarenkorbpos>
    <twarenkorbpos>
      <cName>TEMU Versand</cName>
      <cArtNr/>
      <cBarcode/>
      <cEinheit/>
      <fPreisEinzelNetto>2.51000</fPreisEinzelNetto>
      <fPreis>2.99</fPreis>
      <fMwSt>19.00</fMwSt>
      <fAnzahl>1.00</fAnzahl>
      <cPosTyp>versandkosten</cPosTyp>
      <fRabatt>0.00</fRabatt>
    </twarenkorbpos>
    <tkunde>
      <cKundenNr/>
      <cAnrede/>
      <cTitel/>
      <cVorname>******</cVorname>
      <cNachname>******</cNachname>
      <cFirma/>
      <cStrasse>*****************</cStrasse>
      <cAdressZusatz/>
      <cPLZ>53925	</cPLZ>
      <cOrt>****</cOrt>
      <cBundesland>*******************</cBundesland>
      <cLand>DE</cLand>
      <cTel/>
      <cMobil/>
      <cFax/>
      <cMail/>
      <cUSTID/>
      <cWWW/>
      <cHerkunft>TEMU</cHerkunft>
      <dErstellt>22.11.2025</dErstellt>
    </tkunde>
    <tlieferadresse>
      <cAnrede/>
      <cVorname>******</cVorname>
      <cNachname>******</cNachname>
      <cTitel/>
      <cFirma/>
      <cStrasse>*****************</cStrasse>
      <cAdressZusatz/>
      <cPLZ>53925	</cPLZ>
      <cOrt>****</cOrt>
      <cBundesland>*******************</cBundesland>
      <cLand>DE</cLand>
      <cTel/>
      <cMobil/>
      <cFax/>
      <cMail/>
    </tlieferadresse>
    <tzahlungsinfo>
      <cBankName/>
      <cBLZ/>
      <cKontoNr/>
      <cKartenNr/>
      <dGueltigkeit/>
      <cCVV/>
      <cKartenTyp/>
      <cInhaber/>
      <cIBAN/>
      <cBIC/>
    </tzahlungsinfo>
  </tBestellung>
  <tBestellung kFirma="1" kBenutzer="1">
    <cSprache>ger</cSprache>
    <cWaehrung>EUR</cWaehrung>
    <cBestellNr/>
    <cExterneBestellNr>PO-076-13610953649271673</cExterneBestellNr>
    <cVersandartName>TEMU</cVersandartName>
    <cVersandInfo/>
    <dVersandDatum/>
    <cTracking/>
    <dLieferDatum/>
    <cKommentar/>
    <cBemerkung/>
    <dErstellt>21.11.2025</dErstellt>
    <cZahlungsartName>TEMU</cZahlungsartName>
    <dBezahltDatum/>
    <twarenkorbpos>
      <cName>ToCi 4 x LED Kerzen Dunkelrot Ø 5 x 7 cm &#8211; Flammenlose Echtwachskerzen mit flackerndem Licht &amp; Timer - LED-Stumpenkerzen mit An-/Ausschalter - Batteriebetriebene Dekokerzen für Advent &amp; Zuhause</cName>
      <cArtNr>2021451277-4</cArtNr>
      <cBarcode/>
      <cEinheit/>
      <fPreisEinzelNetto>16.66000</fPreisEinzelNetto>
      <fPreis>19.83</fPreis>
      <fMwSt>19.00</fMwSt>
      <fAnzahl>1.00</fAnzahl>
      <cPosTyp>standard</cPosTyp>
      <fRabatt>0.00</fRabatt>
    </twarenkorbpos>
    <twarenkorbpos>
      <cName>TEMU Versand</cName>
      <cArtNr/>
      <cBarcode/>
      <cEinheit/>
      <fPreisEinzelNetto>2.51000</fPreisEinzelNetto>
      <fPreis>2.99</fPreis>
      <fMwSt>19.00</fMwSt>
      <fAnzahl>1.00</fAnzahl>
      <cPosTyp>versandkosten</cPosTyp>
      <fRabatt>0.00</fRabatt>
    </twarenkorbpos>
    <tkunde>
      <cKundenNr/>
      <cAnrede/>
      <cTitel/>
      <cVorname>******</cVorname>
      <cNachname>************</cNachname>
      <cFirma/>
      <cStrasse>****************</cStrasse>
      <cAdressZusatz/>
      <cPLZ>29471	</cPLZ>
      <cOrt>******</cOrt>
      <cBundesland>*************</cBundesland>
      <cLand>DE</cLand>
      <cTel/>
      <cMobil/>
      <cFax/>
      <cMail/>
      <cUSTID/>
      <cWWW/>
      <cHerkunft>TEMU</cHerkunft>
      <dErstellt>21.11.2025</dErstellt>
    </tkunde>
    <tlieferadresse>
      <cAnrede/>
      <cVorname>******</cVorname>
      <cNachname>************</cNachname>
      <cTitel/>
      <cFirma/>
      <cStrasse>****************</cStrasse>
      <cAdressZusatz/>
      <cPLZ>29471	</cPLZ>
      <cOrt>******</cOrt>
      <cBundesland>*************</cBundesland>
      <cLand>DE</cLand>
      <cTel/>
      <cMobil/>
      <cFax/>
      <cMail/>
    </tlieferadresse>
    <tzahlungsinfo>
      <cBankName/>
      <cBLZ/>
      <cKontoNr/>
      <cKartenNr/>
      <dGueltigkeit/>
      <cCVV/>
      <cKartenTyp/>
      <cInhaber/>
      <cIBAN/>
      <cBIC/>
    </tzahlungsinfo>
  </tBestellung>
  <tBestellung kFirma="1" kBenutzer="1">
    <cSprache>ger</cSprache>
    <cWaehrung>EUR</cWaehrung>
    <cBestellNr/>
    <cExterneBestellNr>PO-076-18616847544952843</cExterneBestellNr>
    <cVersandartName>TEMU</cVersandartName>
    <cVersandInfo/>
    <dVersandDatum/>
    <cTracking/>
    <dLieferDatum/>
    <cKommentar/>
    <cBemerkung/>
    <dErstellt>23.11.2025</dErstellt>
    <cZahlungsartName>TEMU</cZahlungsartName>
    <dBezahltDatum/>
    <twarenkorbpos>
      <cName>ToCi 4 x LED Kerzen Dunkelrot Ø 5 x 7 cm &#8211; Flammenlose Echtwachskerzen mit flackerndem Licht &amp; Timer - LED-Stumpenkerzen mit An-/Ausschalter - Batteriebetriebene Dekokerzen für Advent &amp; Zuhause</cName>
      <cArtNr>2021451277-4</cArtNr>
      <cBarcode/>
      <cEinheit/>
      <fPreisEinzelNetto>16.66000</fPreisEinzelNetto>
      <fPreis>19.83</fPreis>
      <fMwSt>19.00</fMwSt>
      <fAnzahl>1.00</fAnzahl>
      <cPosTyp>standard</cPosTyp>
      <fRabatt>0.00</fRabatt>
    </twarenkorbpos>
    <twarenkorbpos>
      <cName>TEMU Versand</cName>
      <cArtNr/>
      <cBarcode/>
      <cEinheit/>
      <fPreisEinzelNetto>2.51000</fPreisEinzelNetto>
      <fPreis>2.99</fPreis>
      <fMwSt>19.00</fMwSt>
      <fAnzahl>1.00</fAnzahl>
      <cPosTyp>versandkosten</cPosTyp>
      <fRabatt>0.00</fRabatt>
    </twarenkorbpos>
    <tkunde>
      <cKundenNr/>
      <cAnrede/>
      <cTitel/>
      <cVorname>*****</cVorname>
      <cNachname>*****</cNachname>
      <cFirma/>
      <cStrasse>************************</cStrasse>
      <cAdressZusatz/>
      <cPLZ>21033	</cPLZ>
      <cOrt>*******</cOrt>
      <cBundesland>*******</cBundesland>
      <cLand>DE</cLand>
      <cTel/>
      <cMobil/>
      <cFax/>
      <cMail/>
      <cUSTID/>
      <cWWW/>
      <cHerkunft>TEMU</cHerkunft>
      <dErstellt>23.11.2025</dErstellt>
    </tkunde>
    <tlieferadresse>
      <cAnrede/>
      <cVorname>*****</cVorname>
      <cNachname>*****</cNachname>
      <cTitel/>
      <cFirma/>
      <cStrasse>************************</cStrasse>
      <cAdressZusatz/>
      <cPLZ>21033	</cPLZ>
      <cOrt>*******</cOrt>
      <cBundesland>*******</cBundesland>
      <cLand>DE</cLand>
      <cTel/>
      <cMobil/>
      <cFax/>
      <cMail/>
    </tlieferadresse>
    <tzahlungsinfo>
      <cBankName/>
      <cBLZ/>
      <cKontoNr/>
      <cKartenNr/>
      <dGueltigkeit/>
      <cCVV/>
      <cKartenTyp/>
      <cInhaber/>
      <cIBAN/>
      <cBIC/>
    </tzahlungsinfo>
  </tBestellung>
  <tBestellung kFirma="1" kBenutzer="1">
    <cSprache>ger</cSprache>
    <cWaehrung>EUR</cWaehrung>
    <cBestellNr/>
    <cExterneBestellNr>PO-076-18846061310073237</cExterneBestellNr>
    <cVersandartName>TEMU</cVersandartName>
    <cVersandInfo/>
    <dVersandDatum/>
    <cTracking/>
    <dLieferDatum/>
    <cKommentar/>
    <cBemerkung/>
    <dErstellt>23.11.2025</dErstellt>
    <cZahlungsartName>TEMU</cZahlungsartName>
    <dBezahltDatum/>
    <twarenkorbpos>
      <cName>ToCi 4 x LED Kerzen Dunkelrot Ø 5 x 7 cm &#8211; Flammenlose Echtwachskerzen mit flackerndem Licht &amp; Timer - LED-Stumpenkerzen mit An-/Ausschalter - Batteriebetriebene Dekokerzen für Advent &amp; Zuhause</cName>
      <cArtNr>2021451277-4</cArtNr>
      <cBarcode/>
      <cEinheit/>
      <fPreisEinzelNetto>16.66000</fPreisEinzelNetto>
      <fPreis>19.83</fPreis>
      <fMwSt>19.00</fMwSt>
      <fAnzahl>1.00</fAnzahl>
      <cPosTyp>standard</cPosTyp>
      <fRabatt>0.00</fRabatt>
    </twarenkorbpos>
    <twarenkorbpos>
      <cName>TEMU Versand</cName>
      <cArtNr/>
      <cBarcode/>
      <cEinheit/>
      <fPreisEinzelNetto>2.51000</fPreisEinzelNetto>
      <fPreis>2.99</fPreis>
      <fMwSt>19.00</fMwSt>
      <fAnzahl>1.00</fAnzahl>
      <cPosTyp>versandkosten</cPosTyp>
      <fRabatt>0.00</fRabatt>
    </twarenkorbpos>
    <tkunde>
      <cKundenNr/>
      <cAnrede/>
      <cTitel/>
      <cVorname>*********</cVorname>
      <cNachname>**********</cNachname>
      <cFirma/>
      <cStrasse>******************</cStrasse>
      <cAdressZusatz/>
      <cPLZ>84513	</cPLZ>
      <cOrt>*************</cOrt>
      <cBundesland>******</cBundesland>
      <cLand>DE</cLand>
      <cTel/>
      <cMobil/>
      <cFax/>
      <cMail/>
      <cUSTID/>
      <cWWW/>
      <cHerkunft>TEMU</cHerkunft>
      <dErstellt>23.11.2025</dErstellt>
    </tkunde>
    <tlieferadresse>
      <cAnrede/>
      <cVorname>*********</cVorname>
      <cNachname>**********</cNachname>
      <cTitel/>
      <cFirma/>
      <cStrasse>******************</cStrasse>
      <cAdressZusatz/>
      <cPLZ>84513	</cPLZ>
      <cOrt>*************</cOrt>
      <cBundesland>******</cBundesland>
      <cLand>DE</cLand>
      <cTel/>
      <cMobil/>
      <cFax/>
      <cMail/>
    </tlieferadresse>
    <tzahlungsinfo>
      <cBankName/>
      <cBLZ/>
      <cKontoNr/>
      <cKartenNr/>
      <dGueltigkeit/>
      <cCVV/>
      <cKartenTyp/>
      <cInhaber/>
      <cIBAN/>
      <cBIC/>
    </tzahlungsinfo>
  </tBestellung>
  <tBestellung kFirma="1" kBenutzer="1">
    <cSprache>ger</cSprache>
    <cWaehrung>EUR</cWaehrung>
    <cBestellNr/>
    <cExterneBestellNr>PO-076-19026772655990366</cExterneBestellNr>
    <cVersandartName>TEMU</cVersandartName>
    <cVersandInfo/>
    <dVersandDatum/>
    <cTracking/>
    <dLieferDatum/>
    <cKommentar/>
    <cBemerkung/>
    <dErstellt>23.11.2025</dErstellt>
    <cZahlungsartName>TEMU</cZahlungsartName>
    <dBezahltDatum/>
    <twarenkorbpos>
      <cName>ToCi 4 x LED Kerzen Dunkelrot Ø 5 x 7 cm &#8211; Flammenlose Echtwachskerzen mit flackerndem Licht &amp; Timer - LED-Stumpenkerzen mit An-/Ausschalter - Batteriebetriebene Dekokerzen für Advent &amp; Zuhause</cName>
      <cArtNr>2021451277-4</cArtNr>
      <cBarcode/>
      <cEinheit/>
      <fPreisEinzelNetto>16.66000</fPreisEinzelNetto>
      <fPreis>19.83</fPreis>
      <fMwSt>19.00</fMwSt>
      <fAnzahl>1.00</fAnzahl>
      <cPosTyp>standard</cPosTyp>
      <fRabatt>0.00</fRabatt>
    </twarenkorbpos>
    <twarenkorbpos>
      <cName>TEMU Versand</cName>
      <cArtNr/>
      <cBarcode/>
      <cEinheit/>
      <fPreisEinzelNetto>2.51000</fPreisEinzelNetto>
      <fPreis>2.99</fPreis>
      <fMwSt>19.00</fMwSt>
      <fAnzahl>1.00</fAnzahl>
      <cPosTyp>versandkosten</cPosTyp>
      <fRabatt>0.00</fRabatt>
    </twarenkorbpos>
    <tkunde>
      <cKundenNr/>
      <cAnrede/>
      <cTitel/>
      <cVorname>********</cVorname>
      <cNachname>*****</cNachname>
      <cFirma/>
      <cStrasse>*************</cStrasse>
      <cAdressZusatz/>
      <cPLZ>16792	</cPLZ>
      <cOrt>*********</cOrt>
      <cBundesland>***********</cBundesland>
      <cLand>DE</cLand>
      <cTel/>
      <cMobil/>
      <cFax/>
      <cMail/>
      <cUSTID/>
      <cWWW/>
      <cHerkunft>TEMU</cHerkunft>
      <dErstellt>23.11.2025</dErstellt>
    </tkunde>
    <tlieferadresse>
      <cAnrede/>
      <cVorname>********</cVorname>
      <cNachname>*****</cNachname>
      <cTitel/>
      <cFirma/>
      <cStrasse>*************</cStrasse>
      <cAdressZusatz/>
      <cPLZ>16792	</cPLZ>
      <cOrt>*********</cOrt>
      <cBundesland>***********</cBundesland>
      <cLand>DE</cLand>
      <cTel/>
      <cMobil/>
      <cFax/>
      <cMail/>
    </tlieferadresse>
    <tzahlungsinfo>
      <cBankName/>
      <cBLZ/>
      <cKontoNr/>
      <cKartenNr/>
      <dGueltigkeit/>
      <cCVV/>
      <cKartenTyp/>
      <cInhaber/>
      <cIBAN/>
      <cBIC/>
    </tzahlungsinfo>
  </tBestellung>
  <tBestellung kFirma="1" kBenutzer="1">
    <cSprache>ger</cSprache>
    <cWaehrung>EUR</cWaehrung>
    <cBestellNr/>
    <cExterneBestellNr>PO-076-19040316124790319</cExterneBestellNr>
    <cVersandartName>TEMU</cVersandartName>
    <cVersandInfo/>
    <dVersandDatum/>
    <cTracking/>
    <dLieferDatum/>
    <cKommentar/>
    <cBemerkung/>
    <dErstellt>23.11.2025</dErstellt>
    <cZahlungsartName>TEMU</cZahlungsartName>
    <dBezahltDatum/>
    <twarenkorbpos>
      <cName>ToCi 4 x LED Kerzen Dunkelrot Ø 5 x 7 cm &#8211; Flammenlose Echtwachskerzen mit flackerndem Licht &amp; Timer - LED-Stumpenkerzen mit An-/Ausschalter - Batteriebetriebene Dekokerzen für Advent &amp; Zuhause</cName>
      <cArtNr>2021451277-4</cArtNr>
      <cBarcode/>
      <cEinheit/>
      <fPreisEinzelNetto>16.66000</fPreisEinzelNetto>
      <fPreis>19.83</fPreis>
      <fMwSt>19.00</fMwSt>
      <fAnzahl>1.00</fAnzahl>
      <cPosTyp>standard</cPosTyp>
      <fRabatt>0.00</fRabatt>
    </twarenkorbpos>
    <twarenkorbpos>
      <cName>TEMU Versand</cName>
      <cArtNr/>
      <cBarcode/>
      <cEinheit/>
      <fPreisEinzelNetto>2.51000</fPreisEinzelNetto>
      <fPreis>2.99</fPreis>
      <fMwSt>19.00</fMwSt>
      <fAnzahl>1.00</fAnzahl>
      <cPosTyp>versandkosten</cPosTyp>
      <fRabatt>0.00</fRabatt>
    </twarenkorbpos>
    <tkunde>
      <cKundenNr/>
      <cAnrede/>
      <cTitel/>
      <cVorname>******</cVorname>
      <cNachname>******</cNachname>
      <cFirma/>
      <cStrasse>*************</cStrasse>
      <cAdressZusatz/>
      <cPLZ>44141	</cPLZ>
      <cOrt>********</cOrt>
      <cBundesland>*******************</cBundesland>
      <cLand>DE</cLand>
      <cTel/>
      <cMobil/>
      <cFax/>
      <cMail/>
      <cUSTID/>
      <cWWW/>
      <cHerkunft>TEMU</cHerkunft>
      <dErstellt>23.11.2025</dErstellt>
    </tkunde>
    <tlieferadresse>
      <cAnrede/>
      <cVorname>******</cVorname>
      <cNachname>******</cNachname>
      <cTitel/>
      <cFirma/>
      <cStrasse>*************</cStrasse>
      <cAdressZusatz/>
      <cPLZ>44141	</cPLZ>
      <cOrt>********</cOrt>
      <cBundesland>*******************</cBundesland>
      <cLand>DE</cLand>
      <cTel/>
      <cMobil/>
      <cFax/>
      <cMail/>
    </tlieferadresse>
    <tzahlungsinfo>
      <cBankName/>
      <cBLZ/>
      <cKontoNr/>
      <cKartenNr/>
      <dGueltigkeit/>
      <cCVV/>
      <cKartenTyp/>
      <cInhaber/>
      <cIBAN/>
      <cBIC/>
    </tzahlungsinfo>
  </tBestellung>
  <tBestellung kFirma="1" kBenutzer="1">
    <cSprache>ger</cSprache>
    <cWaehrung>EUR</cWaehrung>
    <cBestellNr/>
    <cExterneBestellNr>PO-076-19057247396470472</cExterneBestellNr>
    <cVersandartName>TEMU</cVersandartName>
    <cVersandInfo/>
    <dVersandDatum/>
    <cTracking/>
    <dLieferDatum/>
    <cKommentar/>
    <cBemerkung/>
    <dErstellt>23.11.2025</dErstellt>
    <cZahlungsartName>TEMU</cZahlungsartName>
    <dBezahltDatum/>
    <twarenkorbpos>
      <cName>ToCi 4 x LED Kerzen Dunkelrot Ø 5 x 7 cm &#8211; Flammenlose Echtwachskerzen mit flackerndem Licht &amp; Timer - LED-Stumpenkerzen mit An-/Ausschalter - Batteriebetriebene Dekokerzen für Advent &amp; Zuhause</cName>
      <cArtNr>2021451277-4</cArtNr>
      <cBarcode/>
      <cEinheit/>
      <fPreisEinzelNetto>16.66000</fPreisEinzelNetto>
      <fPreis>19.83</fPreis>
      <fMwSt>19.00</fMwSt>
      <fAnzahl>1.00</fAnzahl>
      <cPosTyp>standard</cPosTyp>
      <fRabatt>0.00</fRabatt>
    </twarenkorbpos>
    <twarenkorbpos>
      <cName>TEMU Versand</cName>
      <cArtNr/>
      <cBarcode/>
      <cEinheit/>
      <fPreisEinzelNetto>2.51000</fPreisEinzelNetto>
      <fPreis>2.99</fPreis>
      <fMwSt>19.00</fMwSt>
      <fAnzahl>1.00</fAnzahl>
      <cPosTyp>versandkosten</cPosTyp>
      <fRabatt>0.00</fRabatt>
    </twarenkorbpos>
    <tkunde>
      <cKundenNr/>
      <cAnrede/>
      <cTitel/>
      <cVorname/>
      <cNachname>***************</cNachname>
      <cFirma/>
      <cStrasse>********************</cStrasse>
      <cAdressZusatz/>
      <cPLZ>35394	</cPLZ>
      <cOrt>******</cOrt>
      <cBundesland>******</cBundesland>
      <cLand>DE</cLand>
      <cTel/>
      <cMobil/>
      <cFax/>
      <cMail/>
      <cUSTID/>
      <cWWW/>
      <cHerkunft>TEMU</cHerkunft>
      <dErstellt>23.11.2025</dErstellt>
    </tkunde>
    <tlieferadresse>
      <cAnrede/>
      <cVorname/>
      <cNachname>***************</cNachname>
      <cTitel/>
      <cFirma/>
      <cStrasse>********************</cStrasse>
      <cAdressZusatz/>
      <cPLZ>35394	</cPLZ>
      <cOrt>******</cOrt>
      <cBundesland>******</cBundesland>
      <cLand>DE</cLand>
      <cTel/>
      <cMobil/>
      <cFax/>
      <cMail/>
    </tlieferadresse>
    <tzahlungsinfo>
      <cBankName/>
      <cBLZ/>
      <cKontoNr/>
      <cKartenNr/>
      <dGueltigkeit/>
      <cCVV/>
      <cKartenTyp/>
      <cInhaber/>
      <cIBAN/>
      <cBIC/>
    </tzahlungsinfo>
  </tBestellung>
</tBestellungen>
